README.md
setup.cfg
setup.py
bee_data_api/__init__.py
bee_data_api/bee_data.py
bee_data_api.egg-info/PKG-INFO
bee_data_api.egg-info/SOURCES.txt
bee_data_api.egg-info/dependency_links.txt
bee_data_api.egg-info/not-zip-safe
bee_data_api.egg-info/requires.txt
bee_data_api.egg-info/top_level.txt