Metadata-Version: 2.1
Name: bee-data-api
Version: 0.50
Summary: UNKNOWN
Home-page: UNKNOWN
Author: steep_11
Author-email: steep1183@gmail.com
License: UNKNOWN
Platform: UNKNOWN
